{
  "ss": {
    "gms": {
      "w": "12",
      "y": "2011",
      "t": "R",
      "gd": "0",
      "bph": "40",
      "g": [
        {
          "eid": "2011112400",
          "gsis": "55324",
          "d": "Thu",
          "t": "12:30",
          "q": "F",
          "h": "DET",
          "hnn": "lions",
          "hs": "15",
          "v": "GB",
          "vnn": "packers",
          "vs": "27",
          "rz": "0",
          "gt": "REG"
        },
        {
          "eid": "2011112401",
          "gsis": "55325",
          "d": "Thu",
          "t": "4:15",
          "q": "F",
          "h": "DAL",
          "hnn": "cowboys",
          "hs": "20",
          "v": "MIA",
          "vnn": "dolphins",
          "vs": "19",
          "rz": "0",
          "gt": "REG"
        },
        {
          "eid": "2011112402",
          "gsis": "55326",
          "d": "Thu",
          "t": "8:20",
          "q": "F",
          "h": "BAL",
          "hnn": "ravens",
          "hs": "16",
          "v": "SF",
          "vnn": "49ers",
          "vs": "6",
          "rz": "0",
          "gt": "REG"
        },
        {
          "eid": "2011112703",
          "gsis": "55327",
          "d": "Sun",
          "t": "1:00",
          "q": "P",
          "h": "ATL",
          "hnn": "falcons",
          "hs": "0",
          "v": "MIN",
          "vnn": "vikings",
          "vs": "0",
          "rz": "0",
          "gt": "REG"
        },
        {
          "eid": "2011112701",
          "gsis": "55328",
          "d": "Sun",
          "t": "1:00",
          "q": "P",
          "h": "CIN",
          "hnn": "bengals",
          "hs": "0",
          "v": "CLE",
          "vnn": "browns",
          "vs": "0",
          "rz": "0",
          "gt": "REG"
        },
        {
          "eid": "2011112705",
          "gsis": "55329",
          "d": "Sun",
          "t": "1:00",
          "q": "P",
          "h": "IND",
          "hnn": "colts",
          "hs": "0",
          "v": "CAR",
          "vnn": "panthers",
          "vs": "0",
          "rz": "0",
          "gt": "REG"
        },
        {
          "eid": "2011112702",
          "gsis": "55330",
          "d": "Sun",
          "t": "1:00",
          "q": "P",
          "h": "JAC",
          "hnn": "jaguars",
          "hs": "0",
          "v": "HOU",
          "vnn": "texans",
          "vs": "0",
          "rz": "0",
          "gt": "REG"
        },
        {
          "eid": "2011112700",
          "gsis": "55331",
          "d": "Sun",
          "t": "1:00",
          "q": "P",
          "h": "NYJ",
          "hnn": "jets",
          "hs": "0",
          "v": "BUF",
          "vnn": "bills",
          "vs": "0",
          "rz": "0",
          "gt": "REG"
        },
        {
          "eid": "2011112704",
          "gsis": "55332",
          "d": "Sun",
          "t": "1:00",
          "q": "P",
          "h": "STL",
          "hnn": "rams",
          "hs": "0",
          "v": "ARI",
          "vnn": "cardinals",
          "vs": "0",
          "rz": "0",
          "gt": "REG"
        },
        {
          "eid": "2011112706",
          "gsis": "55333",
          "d": "Sun",
          "t": "1:00",
          "q": "P",
          "h": "TEN",
          "hnn": "titans",
          "hs": "0",
          "v": "TB",
          "vnn": "buccaneers",
          "vs": "0",
          "rz": "0",
          "gt": "REG"
        },
        {
          "eid": "2011112708",
          "gsis": "55334",
          "d": "Sun",
          "t": "4:05",
          "q": "P",
          "h": "OAK",
          "hnn": "raiders",
          "hs": "0",
          "v": "CHI",
          "vnn": "bears",
          "vs": "0",
          "rz": "0",
          "gt": "REG"
        },
        {
          "eid": "2011112707",
          "gsis": "55335",
          "d": "Sun",
          "t": "4:05",
          "q": "P",
          "h": "SEA",
          "hnn": "seahawks",
          "hs": "0",
          "v": "WAS",
          "vnn": "redskins",
          "vs": "0",
          "rz": "0",
          "gt": "REG"
        },
        {
          "eid": "2011112709",
          "gsis": "55336",
          "d": "Sun",
          "t": "4:15",
          "q": "P",
          "h": "PHI",
          "hnn": "eagles",
          "hs": "0",
          "v": "NE",
          "vnn": "patriots",
          "vs": "0",
          "rz": "0",
          "gt": "REG"
        },
        {
          "eid": "2011112710",
          "gsis": "55337",
          "d": "Sun",
          "t": "4:15",
          "q": "P",
          "h": "SD",
          "hnn": "chargers",
          "hs": "0",
          "v": "DEN",
          "vnn": "broncos",
          "vs": "0",
          "rz": "0",
          "gt": "REG"
        },
        {
          "eid": "2011112711",
          "gsis": "55338",
          "d": "Sun",
          "t": "8:20",
          "q": "P",
          "h": "KC",
          "hnn": "chiefs",
          "hs": "0",
          "v": "PIT",
          "vnn": "steelers",
          "vs": "0",
          "rz": "0",
          "gt": "REG"
        },
        {
          "eid": "2011112800",
          "gsis": "55339",
          "d": "Mon",
          "t": "8:30",
          "q": "P",
          "h": "NO",
          "hnn": "saints",
          "hs": "0",
          "v": "NYG",
          "vnn": "giants",
          "vs": "0",
          "rz": "0",
          "gt": "REG"
        }
      ]
    }
  }
}